wddh/__init__.py
wddh/cli.py
wddh/ltv_reader.py
wddh/mp_threat_dectection_enum.py
wddh/py.typed
wddh/utils.py
wddh/wddh_clean.py
wddh/wddh_part.py
wddh-1.0.0.dist-info/LICENSE
wddh-1.0.0.dist-info/METADATA
wddh-1.0.0.dist-info/WHEEL
wddh-1.0.0.dist-info/entry_points.txt
wddh-1.0.0.dist-info/RECORD
