Metadata-Version: 2.3
Name: wddh
Version: 1.0.0
Summary: Parser for Windows Defender Detection history
License: Apache-2.0
Author: Billaud William
Author-email: william.billaud@orange.com
Requires-Python: <4.0,>=3.10
Classifier: Development Status :: 4 - Beta
Classifier: Environment :: Console
Classifier: Intended Audience :: Developers
Classifier: Intended Audience :: Information Technology
Classifier: License :: OSI Approved
Classifier: Operating System :: OS Independent
Classifier: Programming Language :: Python :: 3
Classifier: Topic :: Scientific/Engineering :: Information Analysis
Classifier: Topic :: Security
Classifier: Topic :: Utilities
Project-URL: Changelog, https://github.com/cert-orangecyberdefense/wddh-parser/blob/master/CHANGELOG.md
Project-URL: Homepage, https://github.com/cert-orangecyberdefense/wddh-parser
Project-URL: Issues, https://github.com/cert-orangecyberdefense/wddh-parser/issues
Project-URL: Repository, https://github.com/cert-orangecyberdefense/wddh-parser.git
